pywikigraph/__init__.py
pywikigraph/wikigraph.py
pywikigraph-0.0.2.dist-info/LICENSE
pywikigraph-0.0.2.dist-info/METADATA
pywikigraph-0.0.2.dist-info/WHEEL
pywikigraph-0.0.2.dist-info/top_level.txt
pywikigraph-0.0.2.dist-info/RECORD
