Metadata-Version: 2.1
Name: pywikigraph
Version: 0.0.2
Summary: Find connection between any two wikipedia topics
Home-page: https://github.com/udemy/pywikigraph
Author: Udemy, Raka Dalal, Sam Cohan
Author-email: opensource@udemy.com
License: UNKNOWN
Keywords: Graph Traversal,WikiGraph,Wikipedia Graph,Bidirectional Search
Platform: UNKNOWN
Classifier: Programming Language :: Python :: 3
Classifier: License :: OSI Approved :: MIT License
Classifier: Operating System :: OS Independent
Requires-Python: >=3.4
Requires-Dist: scipy
